appium_utility/__init__.py
appium_utility/appium_utility.py
appium_utility/decorator.py
appium_utility-0.3.11.dist-info/METADATA
appium_utility-0.3.11.dist-info/WHEEL
appium_utility-0.3.11.dist-info/top_level.txt
appium_utility-0.3.11.dist-info/RECORD
