Metadata-Version: 2.4
Name: appium_utility
Version: 0.3.11
Summary: Reusable Appium utility helpers
Requires-Python: >=3
Requires-Dist: Appium-Python-Client>=4.0.0
Provides-Extra: dev
Requires-Dist: build>=1.3.0; extra == "dev"
Requires-Dist: pre-commit>=4.5.1; extra == "dev"
Requires-Dist: twine>=6.2.0; extra == "dev"
Requires-Dist: mypy>=1.19.1; extra == "dev"
